llama/__init__.py
llama/_llama_cpp_cpu.cpython-312-x86_64-linux-gnu.so
llama/_llama_cpp_cuda_12_6_3.cpython-312-x86_64-linux-gnu.so
llama/_llama_cpp_vulkan_1_x.cpython-312-x86_64-linux-gnu.so
llama/clip.py
llama/context.py
llama/formatter.py
llama/gpu.py
llama/llama_cpp.py
llama/llava.py
llama/minicpmv.py
llama/model.py
llama/options.py
llama/qwen2vl.py
llama/sampler.py
llama/server.py
llama/text.py
llama/util.py
llama_cpp_cffi-0.4.44.dist-info/LICENSE
llama_cpp_cffi-0.4.44.dist-info/METADATA
llama_cpp_cffi-0.4.44.dist-info/WHEEL
llama_cpp_cffi-0.4.44.dist-info/entry_points.txt
llama_cpp_cffi-0.4.44.dist-info/RECORD
