Metadata-Version: 2.3
Name: llama-cpp-cffi
Version: 0.4.44
Summary: Python binding for llama.cpp using cffi
License: MIT
Keywords: llama,llama-cpp,llama.cpp,llama-cpp-cffi,cffi
Author: Tangled Group, Inc
Author-email: info@tangledgroup.com
Requires-Python: >=3.10,<4.0
Classifier: Topic :: Software Development :: Libraries :: Python Modules
Classifier: License :: OSI Approved :: MIT License
Classifier: Programming Language :: Python :: 3
Classifier: Programming Language :: Python :: 3.10
Classifier: Programming Language :: Python :: 3.11
Classifier: Programming Language :: Python :: 3.12
Classifier: Programming Language :: Python :: 3.13
Provides-Extra: server
Requires-Dist: aiohttp[speedups] (>=3.11.12,<4.0.0) ; extra == "server"
Requires-Dist: attrs (>=25.1.0,<26.0.0)
Requires-Dist: gunicorn (==23.0.0) ; extra == "server"
Requires-Dist: huggingface-hub (>=0.28.1,<0.29.0)
Requires-Dist: jinja2 (>=3.1.5,<4.0.0)
Requires-Dist: openai (>=1.63.2,<2.0.0) ; extra == "server"
Requires-Dist: protobuf (>=5.29.3,<6.0.0)
Requires-Dist: psutil (>=7.0.0,<8.0.0)
Requires-Dist: sentencepiece (>=0.2.0,<0.3.0)
Requires-Dist: transformers (>=4.49.0,<5.0.0)
Requires-Dist: uvloop (>=0.21.0,<0.22.0) ; extra == "server"
Project-URL: Bug Tracker, https://github.com/tangledgroup/llama-cpp-cffi/issues
Project-URL: Documentation, https://github.com/tangledgroup/llama-cpp-cffi
Project-URL: Homepage, https://github.com/tangledgroup/llama-cpp-cffi
Project-URL: Repository, https://github.com/tangledgroup/llama-cpp-cffi
